bif
tests
