Metadata-Version: 2.1
Name: bracketed-images-finder
Version: 0.0.3
Summary: Find groups of exposure-bracketed images
Home-page: https://github.com/dsoprea/bracketed_image_finder
Author: Dustin Oprea
Author-email: myselfasunder@gmail.com
License: GPL 2
Keywords: sony bracketing bracketed
Platform: UNKNOWN
